kdotpy/__init__.py
kdotpy/__main__.py
kdotpy/bandtools.py
kdotpy/batchtools.py
kdotpy/berry.py
kdotpy/bhz.py
kdotpy/bhzprint.py
kdotpy/cnp.py
kdotpy/config.py
kdotpy/currents.py
kdotpy/dicttools.py
kdotpy/doc.py
kdotpy/erange.py
kdotpy/errorhandling.py
kdotpy/etransform.py
kdotpy/extrema.py
kdotpy/hdf5o.py
kdotpy/help.py
kdotpy/intervaltools.py
kdotpy/iotools.py
kdotpy/kdotpy-1d.py
kdotpy/kdotpy-2d.py
kdotpy/kdotpy-batch.py
kdotpy/kdotpy-bulk-ll.py
kdotpy/kdotpy-bulk.py
kdotpy/kdotpy-compare.py
kdotpy/kdotpy-config.py
kdotpy/kdotpy-ll.py
kdotpy/kdotpy-merge.py
kdotpy/kdotpy-test.py
kdotpy/latticetrans.py
kdotpy/layerstack.py
kdotpy/lltools.py
kdotpy/main.py
kdotpy/models.py
kdotpy/parallel.py
kdotpy/physconst.py
kdotpy/physparams.py
kdotpy/phystext.py
kdotpy/postprocess.py
kdotpy/resumetools.py
kdotpy/spinmat.py
kdotpy/strain.py
kdotpy/symbolic.py
kdotpy/symmetry.py
kdotpy/tasks.py
kdotpy/testselfcon.py
kdotpy/transitions.py
kdotpy/types.py
kdotpy/version.py
kdotpy/wf.py
kdotpy/bandalign/__init__.py
kdotpy/bandalign/adiabatic.py
kdotpy/bandalign/bandalign.py
kdotpy/bandalign/base.py
kdotpy/bandalign/csvi.py
kdotpy/cmdargs/__init__.py
kdotpy/cmdargs/base.py
kdotpy/cmdargs/cmdargs.py
kdotpy/cmdargs/custom.py
kdotpy/cmdargs/range.py
kdotpy/cmdargs/tools.py
kdotpy/density/__init__.py
kdotpy/density/base.py
kdotpy/density/broadening.py
kdotpy/density/density.py
kdotpy/density/densitydata.py
kdotpy/density/densityscale.py
kdotpy/density/densityz.py
kdotpy/density/elements.py
kdotpy/density/intobs.py
kdotpy/diagonalization/__init__.py
kdotpy/diagonalization/diagdata.py
kdotpy/diagonalization/diagonalization.py
kdotpy/diagonalization/diagsolver.py
kdotpy/diagonalization/feastsolver.py
kdotpy/diagonalization/lldiagonalization.py
kdotpy/diagonalization/stitch.py
kdotpy/docs/helpfile.txt
kdotpy/hamiltonian/__init__.py
kdotpy/hamiltonian/blocks.py
kdotpy/hamiltonian/full.py
kdotpy/hamiltonian/hamiltonian.py
kdotpy/hamiltonian/parity.py
kdotpy/hamiltonian/tools.py
kdotpy-1.3.0.dist-info/entry_points.txt
kdotpy-1.3.0.dist-info/licenses/LICENSE
kdotpy-1.3.0.dist-info/licenses/LICENSE.additional
kdotpy-1.3.0.dist-info/WHEEL
kdotpy-1.3.0.dist-info/METADATA
kdotpy-1.3.0.dist-info/RECORD
