Metadata-Version: 2.4
Name: kdotpy
Version: 1.3.0
Summary: k·p theory on a lattice for simulating semiconductor band structures
Author: Wouter Beugeling, Florian Bayer, Christian Berger, Jan Böttcher, Leonid Bovkun, Christopher Fuchs, Maximilian Hofer, Julian Kuther, Saquib Shamim, Moritz Siebert, Li-Xian Wang, Ewelina M. Hankiewicz, Tobias Kießling, Hartmut Buhmann, Laurens W. Molenkamp
Author-email: kdotpy@uni-wuerzburg.de
Requires-Python: >=3.9
License-Expression: GPL-3.0-only
Classifier: Development Status :: 5 - Production/Stable
Classifier: Programming Language :: Python :: 3
Classifier: Operating System :: POSIX
Classifier: Operating System :: Microsoft :: Windows
Classifier: Intended Audience :: Science/Research
Classifier: Topic :: Scientific/Engineering :: Physics
License-File: LICENSE
License-File: LICENSE.additional
Requires-Dist: numpy>=1.20.0
Requires-Dist: scipy>=1.6.0
Requires-Dist: matplotlib>=3.5.0
Requires-Dist: h5py>=2.8.0 ; extra == "hdf5"
Requires-Dist: pandas>=1.0.0 ; extra == "pandas"
Project-URL: Article, https://doi.org/10.21468/SciPostPhysCodeb.47
Project-URL: Documentation, https://git.physik.uni-wuerzburg.de/kdotpy/kdotpy/-/wikis/home
Project-URL: Homepage, https://kdotpy.physik.uni-wuerzburg.de
Project-URL: Repository, https://git.physik.uni-wuerzburg.de/kdotpy/kdotpy
Provides-Extra: hdf5
Provides-Extra: pandas
